aiogram_callback_manager/__init__.py
aiogram_callback_manager/async_callback_manager.py
aiogram_callback_manager/base_db_storage.py
aiogram_callback_manager-0.1.0.dist-info/LICENSE
aiogram_callback_manager-0.1.0.dist-info/METADATA
aiogram_callback_manager-0.1.0.dist-info/WHEEL
aiogram_callback_manager-0.1.0.dist-info/top_level.txt
aiogram_callback_manager-0.1.0.dist-info/RECORD
